pytransflow/__init__.py
pytransflow/core/__init__.py
pytransflow/core/analyzer.py
pytransflow/core/condition.py
pytransflow/core/configuration.py
pytransflow/core/constants.py
pytransflow/core/controller.py
pytransflow/core/eval.py
pytransflow/core/flow/__init__.py
pytransflow/core/flow/configuration.py
pytransflow/core/flow/dataset.py
pytransflow/core/flow/fail_scenario.py
pytransflow/core/flow/flow.py
pytransflow/core/flow/loader.py
pytransflow/core/flow/parallel.py
pytransflow/core/flow/pipeline.py
pytransflow/core/flow/schema.py
pytransflow/core/flow/statistics.py
pytransflow/core/flow/variables.py
pytransflow/core/record/__init__.py
pytransflow/core/record/failed.py
pytransflow/core/record/record.py
pytransflow/core/resolver.py
pytransflow/core/schema.py
pytransflow/core/transformation/__init__.py
pytransflow/core/transformation/catalogue.py
pytransflow/core/transformation/configuration.py
pytransflow/core/transformation/exception_handler.py
pytransflow/core/transformation/schema.py
pytransflow/core/transformation/transformation.py
pytransflow/exceptions/__init__.py
pytransflow/exceptions/analyzer.py
pytransflow/exceptions/base.py
pytransflow/exceptions/configuration.py
pytransflow/exceptions/controller.py
pytransflow/exceptions/flow.py
pytransflow/exceptions/records.py
pytransflow/exceptions/transformation.py
pytransflow/transformations/__init__.py
pytransflow/transformations/add_field.py
pytransflow/transformations/flatten.py
pytransflow/transformations/generate_uuid.py
pytransflow/transformations/postfix.py
pytransflow/transformations/prefix.py
pytransflow/transformations/regex_extract.py
pytransflow/transformations/remove_fields.py
pytransflow/transformations/rename.py
pytransflow/transformations/validate.py
pytransflow-0.1.1.dist-info/LICENSE.md
pytransflow-0.1.1.dist-info/METADATA
pytransflow-0.1.1.dist-info/WHEEL
pytransflow-0.1.1.dist-info/entry_points.txt
pytransflow-0.1.1.dist-info/RECORD
