Metadata-Version: 2.1
Name: pytransflow
Version: 0.1.1
Summary: Simple library for record-level processing using flows of transformations defined as YAML files.
License: MIT
Keywords: Flow,Transformation,Record Processing,Data,Pipelines
Author: Vladimir Sivcevic
Author-email: vladsiv@protonmail.com
Maintainer: Vladimir Sivcevic
Maintainer-email: vladsiv@protonmail.com
Requires-Python: >=3.8.11,<4.0.0
Classifier: License :: OSI Approved :: MIT License
Classifier: Programming Language :: Python :: 3
Classifier: Programming Language :: Python :: 3.9
Classifier: Programming Language :: Python :: 3.10
Classifier: Programming Language :: Python :: 3.11
Classifier: Programming Language :: Python :: 3.12
Requires-Dist: PyYAML (>=6.0,<7.0)
Requires-Dist: pydantic (>=2.7.2,<3.0.0)
Requires-Dist: simpleeval (>=0.9.12,<0.10.0)
Requires-Dist: tomli (>=1.2.3,<2.0.0)
